celestra/__init__.py
celestra/py.typed
celestra/advanced/__init__.py
celestra/advanced/cost_optimization.py
celestra/advanced/custom_resource.py
celestra/advanced/dependency_manager.py
celestra/advanced/deployment_strategy.py
celestra/advanced/external_services.py
celestra/advanced/observability.py
celestra/advanced/wait_condition.py
celestra/core/__init__.py
celestra/core/app.py
celestra/core/app_group.py
celestra/core/base_builder.py
celestra/core/resource_generator.py
celestra/core/stateful_app.py
celestra/networking/__init__.py
celestra/networking/companion.py
celestra/networking/health.py
celestra/networking/ingress.py
celestra/networking/network_policy.py
celestra/networking/scaling.py
celestra/networking/service.py
celestra/plugins/__init__.py
celestra/plugins/plugin_base.py
celestra/plugins/plugin_manager.py
celestra/plugins/template_manager.py
celestra/security/__init__.py
celestra/security/rbac.py
celestra/security/secret.py
celestra/security/security_policy.py
celestra/storage/__init__.py
celestra/storage/config_map.py
celestra/utils/__init__.py
celestra/utils/decorators.py
celestra/utils/helpers.py
celestra/validation/__init__.py
celestra/validation/cost_estimator.py
celestra/validation/security_scanner.py
celestra/validation/validator.py
celestra/workloads/__init__.py
celestra/workloads/cron_job.py
celestra/workloads/job.py
celestra/workloads/lifecycle.py
examples/__init__.py
examples/advanced_application_demo.py
examples/complete_platform_demo.py
examples/enterprise_validation_demo.py
examples/kubernetes_yaml_generation_example.py
examples/multiple_ports_showcase.py
examples/rbac_security_demo.py
test/__init__.py
test/test_advanced_features.py
test/test_core_components.py
test/test_examples.py
test/test_integration.py
test/test_networking.py
test/test_observability.py
test/test_output_formats.py
test/test_plugins.py
test/test_run_all.py
test/test_security.py
test/test_validation.py
test/test_workloads.py
test/utils.py
celestra-0.0.2.dist-info/METADATA
celestra-0.0.2.dist-info/WHEEL
celestra-0.0.2.dist-info/entry_points.txt
celestra-0.0.2.dist-info/top_level.txt
celestra-0.0.2.dist-info/RECORD
