Metadata-Version: 2.4
Name: celestra
Version: 0.0.2
Summary: A Python DSL for generating Kubernetes manifests with minimal complexity
Author-email: Shivendra Pratap Singh <shivendrapsingh014@gmail.com>
Maintainer-email: Shivendra Pratap Singh <shivendrapsingh014@gmail.com>
License: MIT
Project-URL: Homepage, https://github.com/sps014/celestra
Project-URL: Documentation, https://sps014.github.io/celestra/
Project-URL: Repository, https://github.com/sps014/celestra
Project-URL: Bug Tracker, https://github.com/sps014/celestra/issues
Project-URL: Source Code, https://github.com/sps014/celestra
Keywords: kubernetes,yaml,docker-compose,helm,infrastructure-as-code,dsl,deployment,cloud-native,devops,containers
Classifier: Development Status :: 4 - Beta
Classifier: Intended Audience :: Developers
Classifier: Intended Audience :: System Administrators
Classifier: License :: OSI Approved :: MIT License
Classifier: Operating System :: OS Independent
Classifier: Programming Language :: Python :: 3
Classifier: Programming Language :: Python :: 3.8
Classifier: Programming Language :: Python :: 3.9
Classifier: Programming Language :: Python :: 3.10
Classifier: Programming Language :: Python :: 3.11
Classifier: Programming Language :: Python :: 3.12
Classifier: Topic :: Software Development :: Libraries :: Python Modules
Classifier: Topic :: System :: Systems Administration
Classifier: Topic :: Utilities
Classifier: Typing :: Typed
Requires-Python: >=3.8
Requires-Dist: PyYAML>=6.0
Provides-Extra: dev
Requires-Dist: pytest>=7.4.0; extra == "dev"
Requires-Dist: pytest-cov>=4.1.0; extra == "dev"
Requires-Dist: pytest-json-report>=1.5.0; extra == "dev"
Requires-Dist: black>=23.7.0; extra == "dev"
Requires-Dist: mypy>=1.5.0; extra == "dev"
Requires-Dist: flake8>=6.0.0; extra == "dev"
Provides-Extra: docs
Requires-Dist: mkdocs>=1.5.0; extra == "docs"
Requires-Dist: mkdocs-material>=9.1.0; extra == "docs"
Requires-Dist: mkdocs-awesome-pages-plugin>=2.9.0; extra == "docs"
Requires-Dist: mkdocstrings[python]>=0.22.0; extra == "docs"
Requires-Dist: pymdown-extensions>=10.0; extra == "docs"
Requires-Dist: mkdocs-mermaid2-plugin>=1.1.0; extra == "docs"
Provides-Extra: all
Requires-Dist: celestra[dev,docs]; extra == "all"
